<?xml version="1.0" encoding="UTF-8" standalone="yes"?>
<contentHaul xmlns:a="http://www.appian.com/ae/types/2009">
    <versionUuid>_a-0000e607-97fd-8000-9be9-011c48011c48_1702514</versionUuid>
    <interface>
        <name>AS_FS_CPS_displayServiceRequests</name>
        <uuid>_a-0000e607-97fd-8000-9be9-011c48011c48_1653699</uuid>
        <description>Displays the service requests for navigation</description>
        <parentUuid>_a-0000e4b1-2fbc-8000-9bc6-011c48011c48_968428</parentUuid>
        <visibility>
            <advertise>false</advertise>
            <hierarchy>true</hierarchy>
            <indexable>true</indexable>
            <quota>false</quota>
            <searchable>true</searchable>
            <system>false</system>
            <unlogged>false</unlogged>
        </visibility>
        <definition>#"SYSTEM_SYSRULES_sectionLayout_v1"(
  label: "",
  contents: {
    #"SYSTEM_SYSRULES_ButtonArrayLayout"(
      marginBelow: "NONE",
      buttons: {
        #"SYSTEM_SYSRULES_forEach"(
          items: ri!serviceRequests,
          expression: #"SYSTEM_SYSRULES_ButtonWidget"(
            label: fv!item.name,
            icon: "life-saver",
            saveInto: a!save(ri!selectedServiceRequest, fv!item),
            size: "SMALL",
            style: if(
              ri!selectedServiceRequest = fv!item,
              "PRIMARY",
              "LINK"
            )
          )
        )
      },
      align: "START"
    )
  },
  divider: "BELOW"
)</definition>
        <namedTypedValue>
            <name>serviceRequests</name>
            <type>
                <name>Variant</name>
                <namespace>http://www.appian.com/ae/types/2009</namespace>
            </type>
        </namedTypedValue>
        <namedTypedValue>
            <name>selectedServiceRequest</name>
            <type>
                <name>Variant</name>
                <namespace>http://www.appian.com/ae/types/2009</namespace>
            </type>
        </namedTypedValue>
        <preferredEditor>interface</preferredEditor>
        <offlineEnabled>false</offlineEnabled>
        <isCustom>false</isCustom>
    </interface>
    <roleMap public="true">
        <role inherit="true" allowForAll="false" name="readers">
            <users/>
            <groups/>
        </role>
        <role inherit="true" allowForAll="false" name="authors">
            <users/>
            <groups/>
        </role>
        <role inherit="true" allowForAll="false" name="administrators">
            <users/>
            <groups/>
        </role>
        <role inherit="false" allowForAll="false" name="denyReaders">
            <users/>
            <groups/>
        </role>
        <role inherit="false" allowForAll="false" name="denyAuthors">
            <users/>
            <groups/>
        </role>
        <role inherit="false" allowForAll="false" name="denyAdministrators">
            <users/>
            <groups/>
        </role>
    </roleMap>
    <typedValue>
        <type>
            <name>RuleTestConfig?list</name>
            <namespace>http://www.appian.com/ae/types/2009</namespace>
        </type>
        <value>
            <el>
                <a:name/>
                <a:ruleInputTestConfigs>
                    <a:value xmlns:xsd="http://www.w3.org/2001/XMLSchema" xmlns:xsi="http://www.w3.org/2001/XMLSchema-instance" xsi:type="xsd:string"/>
                    <a:nameRef>serviceRequests</a:nameRef>
                    <a:id>1</a:id>
                </a:ruleInputTestConfigs>
                <a:ruleInputTestConfigs>
                    <a:value xmlns:xsd="http://www.w3.org/2001/XMLSchema" xmlns:xsi="http://www.w3.org/2001/XMLSchema-instance" xsi:type="xsd:string"/>
                    <a:nameRef>selectedServiceRequest</a:nameRef>
                    <a:id>2</a:id>
                </a:ruleInputTestConfigs>
                <a:assertions xmlns:xsi="http://www.w3.org/2001/XMLSchema-instance" xsi:nil="true"/>
            </el>
        </value>
    </typedValue>
    <history>
        <historyInfo versionUuid="_a-0000e607-97fd-8000-9be9-011c48011c48_1653731"/>
        <historyInfo versionUuid="_a-0000e607-97fd-8000-9be9-011c48011c48_1702514"/>
    </history>
</contentHaul>
