{
  "entityName": "AS_FS_A_Account",
  "pegaClassName": "Data-FS-AAccount",
  "tableName": "AS_FS_A_ACCOUNT",
  "description": "Data type refers to the attributes related to the account audit",
  "module": "FS",
  "attributes": [
    {
      "appianFieldName": "accountAuditId",
      "pegaPropertyName": "Accountauditid",
      "appianDataType": "xsd:int",
      "pegaDataType": "Integer",
      "columnName": "ACCOUNT_AUDIT_ID",
      "required": true,
      "isPrimaryKey": true,
      "isForeignKey": false
    },
    {
      "appianFieldName": "accountId",
      "pegaPropertyName": "Accountid",
      "appianDataType": "xsd:int",
      "pegaDataType": "Integer",
      "columnName": "ACCOUNT_ID",
      "required": false,
      "isPrimaryKey": false,
      "isForeignKey": false
    },
    {
      "appianFieldName": "productAuditId",
      "pegaPropertyName": "Productauditid",
      "appianDataType": "xsd:int",
      "pegaDataType": "Integer",
      "columnName": "PRODUCT_AUDIT_ID",
      "required": false,
      "isPrimaryKey": false,
      "isForeignKey": false
    },
    {
      "appianFieldName": "timestamp",
      "pegaPropertyName": "Timestamp",
      "appianDataType": "xsd:dateTime",
      "pegaDataType": "DateTime",
      "columnName": "TIMESTAMP",
      "required": false,
      "isPrimaryKey": false,
      "isForeignKey": false
    },
    {
      "appianFieldName": "username",
      "pegaPropertyName": "Username",
      "appianDataType": "xsd:string",
      "pegaDataType": "Text",
      "columnName": "USERNAME",
      "required": false,
      "isPrimaryKey": false,
      "isForeignKey": false
    },
    {
      "appianFieldName": "auditActionCode",
      "pegaPropertyName": "Auditactioncode",
      "appianDataType": "xsd:string",
      "pegaDataType": "Text",
      "columnName": "AUDIT_ACTION_CODE",
      "required": false,
      "isPrimaryKey": false,
      "isForeignKey": false
    }
  ],
  "relationships": []
}