{
  "entityName": "AS_IO_R_Template_CustomFields",
  "pegaClassName": "Data-IO-RTemplateCustomFields",
  "tableName": "AS_IO_R_TEMPLATE_CUSTOM_FIELDS",
  "description": "Customizable CDT reserved for additional mapping fields that are used during onboarding creation to select the appropriate task template",
  "module": "IO",
  "attributes": [
    {
      "appianFieldName": "templateCustomFieldsId",
      "pegaPropertyName": "Templatecustomfieldsid",
      "appianDataType": "xsd:int",
      "pegaDataType": "Integer",
      "columnName": "TEMPLATE_CUSTOM_FIELDS_ID",
      "required": true,
      "isPrimaryKey": true,
      "isForeignKey": false
    }
  ],
  "relationships": []
}