{
  "entityName": "AS_IO_OnboardingFundingDetails",
  "pegaClassName": "Data-IO-OnboardingFundingDetails",
  "tableName": "AS_IO_ONBOARDING_FUNDING_DETAILS",
  "description": "Data type for the attributes related to funding details of an onboarding",
  "module": "IO",
  "attributes": [
    {
      "appianFieldName": "fundingDetailsId",
      "pegaPropertyName": "Fundingdetailsid",
      "appianDataType": "xsd:int",
      "pegaDataType": "Integer",
      "columnName": "FUNDING_DETAILS_ID",
      "required": true,
      "isPrimaryKey": true,
      "isForeignKey": false
    },
    {
      "appianFieldName": "estFundingDate",
      "pegaPropertyName": "Estfundingdate",
      "appianDataType": "xsd:date",
      "pegaDataType": "Date",
      "columnName": "EST_FUNDING_DATE",
      "required": false,
      "isPrimaryKey": false,
      "isForeignKey": false
    },
    {
      "appianFieldName": "estFundingValue",
      "pegaPropertyName": "Estfundingvalue",
      "appianDataType": "xsd:double",
      "pegaDataType": "Decimal",
      "columnName": "EST_FUNDING_VALUE",
      "required": false,
      "isPrimaryKey": false,
      "isForeignKey": false
    },
    {
      "appianFieldName": "estValueCurrencyCode",
      "pegaPropertyName": "Estvaluecurrencycode",
      "appianDataType": "xsd:string",
      "pegaDataType": "Text",
      "columnName": "EST_VALUE_CURRENCY_CODE",
      "required": false,
      "isPrimaryKey": false,
      "isForeignKey": false
    },
    {
      "appianFieldName": "actualFundingDate",
      "pegaPropertyName": "Actualfundingdate",
      "appianDataType": "xsd:date",
      "pegaDataType": "Date",
      "columnName": "ACTUAL_FUNDING_DATE",
      "required": false,
      "isPrimaryKey": false,
      "isForeignKey": false
    },
    {
      "appianFieldName": "actualFundingValue",
      "pegaPropertyName": "Actualfundingvalue",
      "appianDataType": "xsd:double",
      "pegaDataType": "Decimal",
      "columnName": "ACTUAL_FUNDING_VALUE",
      "required": false,
      "isPrimaryKey": false,
      "isForeignKey": false
    },
    {
      "appianFieldName": "actualValueCurrencyCode",
      "pegaPropertyName": "Actualvaluecurrencycode",
      "appianDataType": "xsd:string",
      "pegaDataType": "Text",
      "columnName": "ACTUAL_VALUE_CURRENCY_CODE",
      "required": false,
      "isPrimaryKey": false,
      "isForeignKey": false
    },
    {
      "appianFieldName": "createdBy",
      "pegaPropertyName": "Createdby",
      "appianDataType": "xsd:string",
      "pegaDataType": "Text",
      "columnName": "CREATED_BY",
      "required": false,
      "isPrimaryKey": false,
      "isForeignKey": false
    },
    {
      "appianFieldName": "createdDatetime",
      "pegaPropertyName": "Createddatetime",
      "appianDataType": "xsd:dateTime",
      "pegaDataType": "DateTime",
      "columnName": "CREATED_DATETIME",
      "required": false,
      "isPrimaryKey": false,
      "isForeignKey": false
    },
    {
      "appianFieldName": "modifiedBy",
      "pegaPropertyName": "Modifiedby",
      "appianDataType": "xsd:string",
      "pegaDataType": "Text",
      "columnName": "MODIFIED_BY",
      "required": false,
      "isPrimaryKey": false,
      "isForeignKey": false
    },
    {
      "appianFieldName": "modifiedDatetime",
      "pegaPropertyName": "Modifieddatetime",
      "appianDataType": "xsd:dateTime",
      "pegaDataType": "DateTime",
      "columnName": "MODIFIED_DATETIME",
      "required": false,
      "isPrimaryKey": false,
      "isForeignKey": false
    }
  ],
  "relationships": []
}